pyaifchunk/__init_.py
pyaifchunk/core_aifc.py
pyaifchunk/core_chunk.py
pyaifchunk-1.0.dist-info/licenses/LICENSE
pyaifchunk-1.0.dist-info/METADATA
pyaifchunk-1.0.dist-info/WHEEL
pyaifchunk-1.0.dist-info/top_level.txt
pyaifchunk-1.0.dist-info/RECORD
