Metadata-Version: 2.4
Name: pyaifchunk
Version: 1.0
Summary: A re-implementation of the IFF chunk module for reading chunked file data.
Home-page: https://pypi.org/project/PyChunkCore/
Author: wambua
Author-email: swskye17@gmail.com
License: GNU v3
Keywords: pyaifc,pychunk,chunk,IFF,audio,file format,multimedia
Classifier: Environment :: Console
Classifier: Natural Language :: English
Classifier: Operating System :: OS Independent
Classifier: Programming Language :: Python
Classifier: Programming Language :: Python :: 3 :: Only
Classifier: Programming Language :: Python :: 3.12
Classifier: Programming Language :: Python :: 3.13
Classifier: License :: OSI Approved :: GNU General Public License v3 (GPLv3)
Requires-Python: >=3.12
License-File: LICENSE
Dynamic: author
Dynamic: author-email
Dynamic: classifier
Dynamic: description
Dynamic: description-content-type
Dynamic: home-page
Dynamic: keywords
Dynamic: license
Dynamic: license-file
Dynamic: requires-python
Dynamic: summary
